solaredge_interface/__init__.py
solaredge_interface/helpers.py
solaredge_interface/solaredge_api.py
solaredge_interface/utils.py
solaredge_interface/api/SolarEdgeAPI.py
solaredge_interface/api/__init__.py
solaredge_interface/bin/__init__.py
solaredge_interface/bin/solaredge_cli.py
solaredge_interface/cli/__init__.py
solaredge_interface/cli/click.py
solaredge_interface/cli/config.py
solaredge_interface/cli/entrypoints.py
solaredge_interface/exceptions/SolarEdgeInterfaceException.py
solaredge_interface/exceptions/__init__.py
solaredge_interface/utils/__init__.py
solaredge_interface/utils/arg_helper.py
solaredge_interface/utils/http_request.py
solaredge_interface/utils/json.py
solaredge_interface/utils/output.py
solaredge_interface/utils/pandas.py
solaredge_interface/utils/timedates.py
solaredge_interface/utils/url_join.py
solaredge_interface-0.3.2.dist-info/LICENSE
solaredge_interface-0.3.2.dist-info/METADATA
solaredge_interface-0.3.2.dist-info/WHEEL
solaredge_interface-0.3.2.dist-info/entry_points.txt
solaredge_interface-0.3.2.dist-info/top_level.txt
solaredge_interface-0.3.2.dist-info/zip-safe
solaredge_interface-0.3.2.dist-info/RECORD
