Metadata-Version: 2.1
Name: solaredge-interface
Version: 0.3.2
Summary: The SolarEdge Interface provides both a command-line interface and a Python module interface to interact with the SolarEdge API service.
Home-page: https://solaredge-interface.readthedocs.io/
Author: Nicholas de Jong
Author-email: contact@nicholasdejong.com
License: BSD2
Keywords: solar,solaredge,solaredge api,solaredge interface
Platform: UNKNOWN
Classifier: Environment :: Console
Classifier: Intended Audience :: Developers
Classifier: Intended Audience :: Information Technology
Classifier: Programming Language :: Python :: 3.7
Classifier: Programming Language :: Python :: 3.8
Classifier: License :: OSI Approved :: BSD License
Requires-Python: >=3.7.0,<4.0.0
Requires-Dist: click
Requires-Dist: pandas
Requires-Dist: requests
Requires-Dist: pytz
Requires-Dist: python-dateutil
